<films>
<film><id>http://dbpedia.org/resource/Reign_of_Terror_%28film%29</id><titles/><directors><director>http://dbpedia.org/resource/Anthony_Mann</director></directors><writers><writer>http://dbpedia.org/resource/Aeneas_MacKenzie</writer><writer>http://dbpedia.org/resource/Philip_Yordan</writer></writers><actors><actor>http://dbpedia.org/resource/Richard_Basehart</actor><actor>http://dbpedia.org/resource/Robert_Cummings</actor></actors></film><film><id>http://dbpedia.org/resource/Rendezvous_%281935_film%29</id><titles/><directors><director>http://dbpedia.org/resource/Sam_Wood</director><director>http://dbpedia.org/resource/William_K._Howard</director></directors><writers><writer>http://dbpedia.org/resource/Herbert_O._Yardley</writer><writer>http://dbpedia.org/resource/P._J._Wolfson</writer><writer>http://dbpedia.org/resource/Bella_Spewak</writer><writer>http://dbpedia.org/resource/George_Oppenheimer</writer><writer>http://dbpedia.org/resource/Sam_Spewak</writer></writers><actors><actor>http://dbpedia.org/resource/Rosalind_Russell</actor><actor>http://dbpedia.org/resource/William_Powell</actor><actor>http://dbpedia.org/resource/Binnie_Barnes</actor></actors></film><film><id>http://dbpedia.org/resource/Rhythm_on_the_River</id><titles/><directors><director>http://dbpedia.org/resource/Victor_Schertzinger</director></directors><writers><writer>http://dbpedia.org/resource/Billy_Wilder</writer><writer>http://dbpedia.org/resource/Dwight_Taylor</writer><writer>http://dbpedia.org/resource/Jacques_Th%C3%A9ry</writer></writers><actors><actor>http://dbpedia.org/resource/Bing_Crosby</actor><actor>http://dbpedia.org/resource/Basil_Rathbone</actor><actor>http://dbpedia.org/resource/Mary_Martin</actor></actors></film><film><id>http://dbpedia.org/resource/Robert_Kennedy_Remembered</id><titles/><directors/><writers/><actors><actor>http://dbpedia.org/resource/Robert_F._Kennedy</actor></actors></film><film><id>http://dbpedia.org/resource/The_Public_Pays</id><titles/><directors><director>http://dbpedia.org/resource/Errol_Taggart</director></directors><writers><writer>http://dbpedia.org/resource/John_C._Higgins</writer></writers><actors><actor>http://dbpedia.org/resource/Barbara_Bedford_%28actor%29</actor><actor>http://dbpedia.org/resource/Richard_Alexander_%28actor%29</actor></actors></film><film><id>http://dbpedia.org/resource/The_Organization_%28film%29</id><titles/><directors><director>http://dbpedia.org/resource/Don_Medford</director></directors><writers/><actors><actor>http://dbpedia.org/resource/Barbara_McNair</actor><actor>http://dbpedia.org/resource/Sidney_Poitier</actor></actors></film><film><id>http://dbpedia.org/resource/Quicker%27n_a_Wink</id><titles/><directors><director>http://dbpedia.org/resource/George_Sidney</director></directors><writers><writer>http://dbpedia.org/resource/Buddy_Adler</writer></writers><actors><actor>http://dbpedia.org/resource/Harold_Eugene_Edgerton</actor></actors></film><film><id>http://dbpedia.org/resource/Of_Pups_and_Puzzles</id><titles/><directors><director>http://dbpedia.org/resource/George_Sidney</director></directors><writers/><actors><actor>http://dbpedia.org/resource/Eddy_Chandler</actor></actors></film><film><id>http://dbpedia.org/resource/Speaking_of_Animals_and_Their_Families</id><titles/><directors><director>http://dbpedia.org/resource/Jerry_Fairbanks</director></directors><writers/><actors><actor>http://dbpedia.org/resource/Gayne_Whitman</actor></actors></film><film><id>http://dbpedia.org/resource/Lucky_Cisco_Kid</id><titles/><directors><director>http://dbpedia.org/resource/H._Bruce_Humberstone</director></directors><writers/><actors><actor>http://dbpedia.org/resource/Dana_Andrews</actor><actor>http://dbpedia.org/resource/Mary_Beth_Hughes</actor><actor>http://dbpedia.org/resource/Cesar_Romero</actor></actors></film><film><id>http://dbpedia.org/resource/A_Boy_and_His_Dog_%28film%29</id><titles/><directors><director>http://dbpedia.org/resource/LeRoy_Prinz</director></directors><writers/><actors><actor>http://dbpedia.org/resource/Harry_Davenport</actor></actors></film><film><id>http://dbpedia.org/resource/Goodbye%2C_Miss_Turlock</id><titles/><directors><director>http://dbpedia.org/resource/Edward_Cahn_%28director%29</director></directors><writers/><actors/></film><film><id>http://dbpedia.org/resource/Climbing_the_Matterhorn</id><titles/><directors><director>http://dbpedia.org/resource/Irving_Allen</director></directors><writers/><actors/></film><film><id>http://dbpedia.org/resource/Bear_Country_%28film%29</id><titles/><directors><director>http://dbpedia.org/resource/James_Algar</director></directors><writers><writer>http://dbpedia.org/resource/James_Algar</writer></writers><actors><actor>http://dbpedia.org/resource/Winston_Hibler</actor></actors></film><film><id>http://dbpedia.org/resource/This_Mechanical_Age</id><titles/><directors/><writers/><actors/></film><film><id>http://dbpedia.org/resource/A_Time_Out_of_War</id><titles/><directors><director>http://dbpedia.org/resource/Denis_Sanders</director></directors><writers/><actors><actor>http://dbpedia.org/resource/Barry_Atwater</actor><actor>http://dbpedia.org/resource/Corey_Allen</actor></actors></film><film><id>http://dbpedia.org/resource/Survival_City</id><titles/><directors/><writers/><actors/></film><film><id>http://dbpedia.org/resource/Grand_Canyon_%281958_film%29</id><titles/><directors><director>http://dbpedia.org/resource/James_Algar</director></directors><writers/><actors/></film><film><id>http://dbpedia.org/resource/The_Diary_of_a_Chambermaid_%281946_film%29</id><titles/><directors><director>http://dbpedia.org/resource/Jean_Renoir</director></directors><writers><writer>http://dbpedia.org/resource/Octave_Mirbeau</writer><writer>http://dbpedia.org/resource/Andr%C3%A9_de_Lorde</writer><writer>http://dbpedia.org/resource/Andr%C3%A9_Heuse</writer><writer>http://dbpedia.org/resource/Thielly_Nores</writer></writers><actors><actor>http://dbpedia.org/resource/Francis_Lederer</actor><actor>http://dbpedia.org/resource/Hurd_Hatfield</actor></actors></film><film><id>http://dbpedia.org/resource/Up_%281984_film%29</id><titles/><directors/><writers/><actors/></film><film><id>http://dbpedia.org/resource/Fiddlesticks_%28film%29</id><titles/><directors/><writers/><actors/></film><film><id>http://dbpedia.org/resource/Two_Soldiers</id><titles/><directors><director>http://dbpedia.org/resource/Aaron_Schneider</director></directors><writers><writer>http://dbpedia.org/resource/William_Faulkner</writer><writer>http://dbpedia.org/resource/Aaron_Schneider</writer></writers><actors><actor>http://dbpedia.org/resource/Ben_Allison</actor><actor>http://dbpedia.org/resource/Jonathan_Furr</actor></actors></film><film><id>http://dbpedia.org/resource/Two_Guys_from_Texas</id><titles/><directors/><writers/><actors/></film><film><id>http://dbpedia.org/resource/Why_Korea%3F</id><titles/><directors/><writers/><actors/></film><film><id>http://dbpedia.org/resource/The_Alaskan_Eskimo</id><titles/><directors/><writers/><actors/></film><film><id>http://dbpedia.org/resource/The_True_Story_of_the_Civil_War</id><titles/><directors><director>http://dbpedia.org/resource/Louis_Clyde_Stoumen</director></directors><writers/><actors/></film><film><id>http://dbpedia.org/resource/The_Dukes_%28film%29</id><titles/><directors/><writers/><actors><actor>http://dbpedia.org/resource/Chazz_Palminteri</actor><actor>http://dbpedia.org/resource/Robert_Davi</actor><actor>http://dbpedia.org/resource/Peter_Bogdanovich</actor></actors></film><film><id>http://dbpedia.org/resource/The_Three_Musketeers_%281969_film%29</id><titles/><directors/><writers/><actors/></film><film><id>http://dbpedia.org/resource/The_Flight_of_the_Gossamer_Condor</id><titles/><directors><director>http://dbpedia.org/resource/Ben_Shedd</director></directors><writers/><actors><actor>http://dbpedia.org/resource/Bryan_Allen_%28hang_glider%29</actor></actors></film><film><id>http://dbpedia.org/resource/Witness_to_War:_Dr._Charlie_Clements</id><titles/><directors><director>http://dbpedia.org/resource/Deborah_Shaffer</director></directors><writers/><actors/></film><film><id>http://dbpedia.org/resource/Young_at_Heart_%281987_film%29</id><titles/><directors/><writers/><actors/></film><film><id>http://dbpedia.org/resource/The_Fall_%282008_film%29</id><titles/><directors><director>http://dbpedia.org/resource/Tarsem_Singh</director></directors><writers><writer>http://dbpedia.org/resource/Dan_Gilroy</writer><writer>http://dbpedia.org/resource/Nico_Soultanakis</writer></writers><actors><actor>http://dbpedia.org/resource/Justine_Waddell</actor><actor>http://dbpedia.org/resource/Lee_Pace</actor><actor>http://dbpedia.org/resource/Catinca_Untaru</actor></actors></film><film><id>http://dbpedia.org/resource/Confessions_of_an_Opium_Eater</id><titles/><directors/><writers/><actors><actor>http://dbpedia.org/resource/Richard_Loo</actor><actor>http://dbpedia.org/resource/Philip_Ahn</actor></actors></film><film><id>http://dbpedia.org/resource/The_Butler%27s_in_Love</id><titles/><directors><director>http://dbpedia.org/resource/David_Arquette</director></directors><writers/><actors><actor>http://dbpedia.org/resource/Thomas_Jane</actor><actor>http://dbpedia.org/resource/Elizabeth_Berkley</actor><actor>http://dbpedia.org/resource/Richmond_Arquette</actor></actors></film><film><id>http://dbpedia.org/resource/What%2C_No_Men%21</id><titles/><directors><director>http://dbpedia.org/resource/Ralph_Staub</director></directors><writers/><actors><actor>http://dbpedia.org/resource/El_Brendel</actor></actors></film><film><id>http://dbpedia.org/resource/The_Man_Without_a_Country_%281937_film%29</id><titles/><directors><director>http://dbpedia.org/resource/Crane_Wilbur</director></directors><writers><writer>http://dbpedia.org/resource/Edward_Everett_Hale</writer></writers><actors><actor>http://dbpedia.org/resource/Gloria_Holden</actor><actor>http://dbpedia.org/resource/John_Litel</actor></actors></film><film><id>http://dbpedia.org/resource/The_Girl_of_the_Golden_West_%281938_film%29</id><titles/><directors><director>http://dbpedia.org/resource/Robert_Z._Leonard</director></directors><writers><writer>http://dbpedia.org/resource/David_Belasco</writer><writer>http://dbpedia.org/resource/Isabel_Dawn</writer><writer>http://dbpedia.org/resource/Boyce_DeGaw</writer></writers><actors><actor>http://dbpedia.org/resource/Nelson_Eddy</actor><actor>http://dbpedia.org/resource/Walter_Pidgeon</actor><actor>http://dbpedia.org/resource/Jeanette_MacDonald</actor></actors></film><film><id>http://dbpedia.org/resource/The_Big_Bird_Cage</id><titles/><directors><director>http://dbpedia.org/resource/Jack_Hill</director></directors><writers/><actors><actor>http://dbpedia.org/resource/Pam_Grier</actor><actor>http://dbpedia.org/resource/Carol_Speed</actor><actor>http://dbpedia.org/resource/Sid_Haig</actor><actor>http://dbpedia.org/resource/Anitra_Ford</actor></actors></film><film><id>http://dbpedia.org/resource/Turnabout_%28film%29</id><titles/><directors><director>http://dbpedia.org/resource/Hal_Roach</director></directors><writers><writer>http://dbpedia.org/resource/Rian_James</writer><writer>http://dbpedia.org/resource/Thorne_Smith</writer></writers><actors><actor>http://dbpedia.org/resource/Carole_Landis</actor><actor>http://dbpedia.org/resource/Adolphe_Menjou</actor><actor>http://dbpedia.org/resource/John_Hubbard_%28actor%29</actor></actors></film><film><id>http://dbpedia.org/resource/The_Haunted_Bedroom</id><titles/><directors><director>http://dbpedia.org/resource/Fred_Niblo</director></directors><writers><writer>http://dbpedia.org/resource/C._Gardner_Sullivan</writer></writers><actors><actor>http://dbpedia.org/resource/Enid_Bennett</actor></actors></film><film><id>http://dbpedia.org/resource/The_Virtuous_Thief</id><titles/><directors><director>http://dbpedia.org/resource/Fred_Niblo</director></directors><writers><writer>http://dbpedia.org/resource/C._Gardner_Sullivan</writer></writers><actors><actor>http://dbpedia.org/resource/Enid_Bennett</actor><actor>http://dbpedia.org/resource/Niles_Welch</actor></actors></film><film><id>http://dbpedia.org/resource/The_Famous_Mrs._Fair</id><titles/><directors><director>http://dbpedia.org/resource/Fred_Niblo</director></directors><writers><writer>http://dbpedia.org/resource/James_Forbes_%28screenwriter%29</writer><writer>http://dbpedia.org/resource/Frances_Marion</writer></writers><actors><actor>http://dbpedia.org/resource/Huntley_Gordon</actor><actor>http://dbpedia.org/resource/Myrtle_Stedman</actor></actors></film><film><id>http://dbpedia.org/resource/The_Blood_Red_Tape_of_Charity</id><titles/><directors><director>http://dbpedia.org/resource/Edwin_August</director></directors><writers/><actors><actor>http://dbpedia.org/resource/Lon_Chaney%2C_Sr.</actor><actor>http://dbpedia.org/resource/Edwin_August</actor></actors></film><film><id>http://dbpedia.org/resource/The_Trap_%281913_film%29</id><titles/><directors><director>http://dbpedia.org/resource/Edwin_August</director></directors><writers/><actors><actor>http://dbpedia.org/resource/Pauline_Bush_%28actress%29</actor><actor>http://dbpedia.org/resource/Murdock_MacQuarrie</actor></actors></film><film><id>http://dbpedia.org/resource/The_Bat_Whispers</id><titles/><directors><director>http://dbpedia.org/resource/Roland_West</director></directors><writers><writer>http://dbpedia.org/resource/Mary_Roberts_Rinehart</writer><writer>http://dbpedia.org/resource/Avery_Hopwood</writer><writer>http://dbpedia.org/resource/Roland_West</writer></writers><actors><actor>http://dbpedia.org/resource/Chester_Morris</actor></actors></film><film><id>http://dbpedia.org/resource/The_Doll_%282008_film%29</id><titles/><directors><director>http://dbpedia.org/resource/Dante_J._James</director></directors><writers><writer>http://dbpedia.org/resource/Dante_J._James</writer></writers><actors><actor>http://dbpedia.org/resource/Clayton_LeBouef</actor><actor>http://dbpedia.org/resource/Larry_E._Hull</actor><actor>http://dbpedia.org/resource/Joseph_A._Boone</actor><actor>http://dbpedia.org/resource/Carter_Jahncke</actor><actor>http://dbpedia.org/resource/Monique_Brown</actor><actor>http://dbpedia.org/resource/Jan_Forbes</actor></actors></film><film><id>http://dbpedia.org/resource/The_Red_Menace_%28film%29</id><titles/><directors><director>http://dbpedia.org/resource/R._G._Springsteen</director></directors><writers><writer>http://dbpedia.org/resource/Albert_DeMond</writer><writer>http://dbpedia.org/resource/Gerald_Geraghty</writer></writers><actors><actor>http://dbpedia.org/resource/Betty_Lou_Gerson</actor><actor>http://dbpedia.org/resource/Robert_Rockwell</actor><actor>http://dbpedia.org/resource/Hannelore_Axman</actor></actors></film><film><id>http://dbpedia.org/resource/The_Lamb%2C_the_Woman%2C_the_Wolf</id><titles/><directors><director>http://dbpedia.org/resource/Allan_Dwan</director></directors><writers><writer>http://dbpedia.org/resource/Allan_Dwan</writer></writers><actors><actor>http://dbpedia.org/resource/Pauline_Bush_%28actress%29</actor><actor>http://dbpedia.org/resource/Lon_Chaney%2C_Sr.</actor><actor>http://dbpedia.org/resource/Murdock_MacQuarrie</actor></actors></film><film><id>http://dbpedia.org/resource/The_Forbidden_Room</id><titles/><directors><director>http://dbpedia.org/resource/Allan_Dwan</director></directors><writers><writer>http://dbpedia.org/resource/Bess_Meredyth</writer></writers><actors><actor>http://dbpedia.org/resource/Pauline_Bush_%28actress%29</actor><actor>http://dbpedia.org/resource/Murdock_MacQuarrie</actor></actors></film><film><id>http://dbpedia.org/resource/The_Beautiful_Blonde_from_Bashful_Bend</id><titles/><directors><director>http://dbpedia.org/resource/Preston_Sturges</director></directors><writers/><actors><actor>http://dbpedia.org/resource/Betty_Grable</actor></actors></film><film><id>http://dbpedia.org/resource/The_Lion%2C_the_Lamb%2C_the_Man</id><titles/><directors><director>http://dbpedia.org/resource/Joe_De_Grasse</director></directors><writers/><actors><actor>http://dbpedia.org/resource/Pauline_Bush_%28actress%29</actor><actor>http://dbpedia.org/resource/Lon_Chaney%2C_Sr.</actor></actors></film><film><id>http://dbpedia.org/resource/The_Natural_History_of_Parking_Lots</id><titles/><directors><director>http://dbpedia.org/resource/Everett_Lewis</director></directors><writers><writer>http://dbpedia.org/resource/Everett_Lewis</writer></writers><actors><actor>http://dbpedia.org/resource/B._Wyatt</actor><actor>http://dbpedia.org/resource/Charlie_Bean_%28actor%29</actor><actor>http://dbpedia.org/resource/Charles_Taylor_%28actor%29</actor></actors></film><film><id>http://dbpedia.org/resource/The_Threads_of_Fate</id><titles/><directors><director>http://dbpedia.org/resource/Joe_De_Grasse</director></directors><writers><writer>http://dbpedia.org/resource/Tom_Forman</writer></writers><actors><actor>http://dbpedia.org/resource/Pauline_Bush_%28actress%29</actor><actor>http://dbpedia.org/resource/Lon_Chaney%2C_Sr.</actor></actors></film><film><id>http://dbpedia.org/resource/The_Escape_%281914_film%29</id><titles/><directors><director>http://dbpedia.org/resource/D._W._Griffith</director></directors><writers><writer>http://dbpedia.org/resource/D._W._Griffith</writer></writers><actors><actor>http://dbpedia.org/resource/Donald_Crisp</actor></actors></film><film><id>http://dbpedia.org/resource/They_Just_Had_to_Get_Married</id><titles/><directors><director>http://dbpedia.org/resource/Edward_Ludwig</director></directors><writers><writer>http://dbpedia.org/resource/Preston_Sturges</writer><writer>http://dbpedia.org/resource/H.M._Walker</writer></writers><actors><actor>http://dbpedia.org/resource/Slim_Summerville</actor><actor>http://dbpedia.org/resource/Verree_Teasdale</actor><actor>http://dbpedia.org/resource/Roland_Young</actor><actor>http://dbpedia.org/resource/Zasu_Pitts</actor></actors></film><film><id>http://dbpedia.org/resource/Hit_the_Deck_%281955_film%29</id><titles/><directors><director>http://dbpedia.org/resource/Roy_Rowland_%28film_director%29</director></directors><writers><writer>http://dbpedia.org/resource/Sonya_Levien</writer></writers><actors><actor>http://dbpedia.org/resource/Jane_Powell</actor></actors></film><film><id>http://dbpedia.org/resource/Maid_of_the_Mist_%281915_film%29</id><titles/><directors><director>http://dbpedia.org/resource/Joe_De_Grasse</director></directors><writers/><actors><actor>http://dbpedia.org/resource/Pauline_Bush_%28actress%29</actor><actor>http://dbpedia.org/resource/Lon_Chaney%2C_Sr.</actor></actors></film><film><id>http://dbpedia.org/resource/The_Stool_Pigeon</id><titles/><directors><director>http://dbpedia.org/resource/Lon_Chaney%2C_Sr.</director></directors><writers/><actors><actor>http://dbpedia.org/resource/Lon_Chaney%2C_Sr.</actor><actor>http://dbpedia.org/resource/J._Warren_Kerrigan</actor></actors></film><film><id>http://dbpedia.org/resource/Steady_Company</id><titles/><directors><director>http://dbpedia.org/resource/Joe_De_Grasse</director></directors><writers><writer>http://dbpedia.org/resource/Ida_May_Park</writer><writer>http://dbpedia.org/resource/Jules_Furthman</writer></writers><actors><actor>http://dbpedia.org/resource/Pauline_Bush_%28actress%29</actor><actor>http://dbpedia.org/resource/Lon_Chaney%2C_Sr.</actor></actors></film><film><id>http://dbpedia.org/resource/The_Violin_Maker</id><titles/><directors><director>http://dbpedia.org/resource/Lon_Chaney%2C_Sr.</director></directors><writers/><actors><actor>http://dbpedia.org/resource/Lon_Chaney%2C_Sr.</actor><actor>http://dbpedia.org/resource/Gretchen_Lederer</actor></actors></film><film><id>http://dbpedia.org/resource/The_Trust_%281915_film%29</id><titles/><directors><director>http://dbpedia.org/resource/Lon_Chaney%2C_Sr.</director></directors><writers/><actors><actor>http://dbpedia.org/resource/Lon_Chaney%2C_Sr.</actor><actor>http://dbpedia.org/resource/Vera_Sisson</actor></actors></film><film><id>http://dbpedia.org/resource/One_Rainy_Afternoon</id><titles/><directors><director>http://dbpedia.org/resource/Rowland_V._Lee</director></directors><writers><writer>http://dbpedia.org/resource/Emeric_Pressburger</writer><writer>http://dbpedia.org/resource/Stephen_Morehouse_Avery</writer></writers><actors><actor>http://dbpedia.org/resource/Francis_Lederer</actor><actor>http://dbpedia.org/resource/Ida_Lupino</actor></actors></film><film><id>http://dbpedia.org/resource/Where_Or_When_%28film%29</id><titles/><directors/><writers/><actors/></film><film><id>http://dbpedia.org/resource/The_Pine%27s_Revenge</id><titles/><directors><director>http://dbpedia.org/resource/Joe_De_Grasse</director></directors><writers><writer>http://dbpedia.org/resource/Nell_Shipman</writer></writers><actors><actor>http://dbpedia.org/resource/Cleo_Madison</actor><actor>http://dbpedia.org/resource/Lon_Chaney%2C_Sr.</actor></actors></film><film><id>http://dbpedia.org/resource/The_Fascination_of_the_Fleur_de_Lis</id><titles/><directors><director>http://dbpedia.org/resource/Joe_De_Grasse</director></directors><writers><writer>http://dbpedia.org/resource/Bess_Meredyth</writer></writers><actors><actor>http://dbpedia.org/resource/Cleo_Madison</actor><actor>http://dbpedia.org/resource/Lon_Chaney%2C_Sr.</actor></actors></film><film><id>http://dbpedia.org/resource/Father_and_the_Boys</id><titles/><directors><director>http://dbpedia.org/resource/Joe_De_Grasse</director></directors><writers><writer>http://dbpedia.org/resource/Ida_May_Park</writer><writer>http://dbpedia.org/resource/George_Ade</writer></writers><actors><actor>http://dbpedia.org/resource/Lon_Chaney%2C_Sr.</actor><actor>http://dbpedia.org/resource/Louise_Lovely</actor></actors></film><film><id>http://dbpedia.org/resource/Dolly%27s_Scoop</id><titles/><directors><director>http://dbpedia.org/resource/Joe_De_Grasse</director></directors><writers><writer>http://dbpedia.org/resource/Ida_May_Park</writer></writers><actors><actor>http://dbpedia.org/resource/Lon_Chaney%2C_Sr.</actor><actor>http://dbpedia.org/resource/Louise_Lovely</actor></actors></film><film><id>http://dbpedia.org/resource/The_Grasp_of_Greed</id><titles/><directors><director>http://dbpedia.org/resource/Joe_De_Grasse</director></directors><writers><writer>http://dbpedia.org/resource/Ida_May_Park</writer><writer>http://dbpedia.org/resource/H._Rider_Haggard</writer></writers><actors><actor>http://dbpedia.org/resource/Lon_Chaney%2C_Sr.</actor><actor>http://dbpedia.org/resource/Louise_Lovely</actor></actors></film><film><id>http://dbpedia.org/resource/David_%26_Fatima</id><titles/><directors><director>http://dbpedia.org/resource/Alain_Zaloum</director></directors><writers><writer>http://dbpedia.org/resource/Randala</writer><writer>http://dbpedia.org/resource/Alain_Zaloum</writer><writer>http://dbpedia.org/resource/Patrick_Krauss</writer><writer>http://dbpedia.org/resource/Kari_Bian</writer></writers><actors><actor>http://dbpedia.org/resource/Martin_Landau</actor><actor>http://dbpedia.org/resource/Cameron_Van_Hoy</actor><actor>http://dbpedia.org/resource/Danielle_Pollack</actor></actors></film><film><id>http://dbpedia.org/resource/New_York_Town</id><titles/><directors><director>http://dbpedia.org/resource/Charles_Vidor</director></directors><writers><writer>http://dbpedia.org/resource/Preston_Sturges</writer><writer>http://dbpedia.org/resource/Jo_Swerling</writer></writers><actors><actor>http://dbpedia.org/resource/Fred_MacMurray</actor><actor>http://dbpedia.org/resource/Robert_Preston_%28actor%29</actor><actor>http://dbpedia.org/resource/Akim_Tamiroff</actor><actor>http://dbpedia.org/resource/Mary_Martin</actor></actors></film><film><id>http://dbpedia.org/resource/Felix_on_the_Job</id><titles/><directors><director>http://dbpedia.org/resource/George_Felix</director></directors><writers/><actors><actor>http://dbpedia.org/resource/Lon_Chaney%2C_Sr.</actor><actor>http://dbpedia.org/resource/George_Felix</actor></actors></film><film><id>http://dbpedia.org/resource/The_Place_Beyond_the_Winds</id><titles/><directors><director>http://dbpedia.org/resource/Joe_De_Grasse</director></directors><writers><writer>http://dbpedia.org/resource/Ida_May_Park</writer></writers><actors><actor>http://dbpedia.org/resource/Lon_Chaney%2C_Sr.</actor><actor>http://dbpedia.org/resource/Dorothy_Phillips</actor></actors></film><film><id>http://dbpedia.org/resource/The_Piper%27s_Price</id><titles/><directors><director>http://dbpedia.org/resource/Joe_De_Grasse</director></directors><writers><writer>http://dbpedia.org/resource/Ida_May_Park</writer></writers><actors><actor>http://dbpedia.org/resource/Lon_Chaney%2C_Sr.</actor><actor>http://dbpedia.org/resource/Dorothy_Phillips</actor></actors></film><film><id>http://dbpedia.org/resource/The_Price_of_Silence_%28film%29</id><titles/><directors><director>http://dbpedia.org/resource/Joe_De_Grasse</director></directors><writers><writer>http://dbpedia.org/resource/Ida_May_Park</writer></writers><actors><actor>http://dbpedia.org/resource/Lon_Chaney%2C_Sr.</actor><actor>http://dbpedia.org/resource/Dorothy_Phillips</actor></actors></film><film><id>http://dbpedia.org/resource/A_Doll%27s_House_%281917_film%29</id><titles/><directors><director>http://dbpedia.org/resource/Joe_De_Grasse</director></directors><writers><writer>http://dbpedia.org/resource/Joe_De_Grasse</writer><writer>http://dbpedia.org/resource/Henrik_Ibsen</writer></writers><actors><actor>http://dbpedia.org/resource/Lon_Chaney%2C_Sr.</actor><actor>http://dbpedia.org/resource/Dorothy_Phillips</actor></actors></film><film><id>http://dbpedia.org/resource/Fires_of_Rebellion</id><titles/><directors><director>http://dbpedia.org/resource/Ida_May_Park</director></directors><writers><writer>http://dbpedia.org/resource/Ida_May_Park</writer></writers><actors><actor>http://dbpedia.org/resource/Lon_Chaney%2C_Sr.</actor><actor>http://dbpedia.org/resource/Dorothy_Phillips</actor></actors></film><film><id>http://dbpedia.org/resource/The_Grand_Passion</id><titles/><directors><director>http://dbpedia.org/resource/Ida_May_Park</director></directors><writers><writer>http://dbpedia.org/resource/Ida_May_Park</writer><writer>http://dbpedia.org/resource/Thomas_Addison</writer></writers><actors><actor>http://dbpedia.org/resource/Lon_Chaney%2C_Sr.</actor><actor>http://dbpedia.org/resource/Dorothy_Phillips</actor></actors></film><film><id>http://dbpedia.org/resource/Riddle_Gawne</id><titles/><directors><director>http://dbpedia.org/resource/William_S._Hart</director><director>http://dbpedia.org/resource/Lambert_Hillyer</director></directors><writers><writer>http://dbpedia.org/resource/Charles_Alden_Seltzer</writer></writers><actors><actor>http://dbpedia.org/resource/Lon_Chaney%2C_Sr.</actor><actor>http://dbpedia.org/resource/William_S._Hart</actor></actors></film><film><id>http://dbpedia.org/resource/The_Talk_of_the_Town_%281918_film%29</id><titles/><directors><director>http://dbpedia.org/resource/Allen_Holubar</director></directors><writers><writer>http://dbpedia.org/resource/Allen_Holubar</writer></writers><actors><actor>http://dbpedia.org/resource/Lon_Chaney%2C_Sr.</actor><actor>http://dbpedia.org/resource/Dorothy_Phillips</actor></actors></film><film><id>http://dbpedia.org/resource/The_Culpepper_Cattle_Co.</id><titles/><directors><director>http://dbpedia.org/resource/Dick_Richards</director></directors><writers><writer>http://dbpedia.org/resource/Dick_Richards</writer></writers><actors><actor>http://dbpedia.org/resource/Billy_Green_Bush</actor><actor>http://dbpedia.org/resource/Gary_Grimes</actor></actors></film><film><id>http://dbpedia.org/resource/The_Two_Orphans_%281915_film%29</id><titles/><directors><director>http://dbpedia.org/resource/Herbert_Brenon</director></directors><writers><writer>http://dbpedia.org/resource/Herbert_Brenon</writer><writer>http://dbpedia.org/resource/Adolphe_d%27Ennery</writer><writer>http://dbpedia.org/resource/Eug%C3%A8ne_Cormon</writer></writers><actors><actor>http://dbpedia.org/resource/Theda_Bara</actor></actors></film><film><id>http://dbpedia.org/resource/Carmen_%281915_Raoul_Walsh_film%29</id><titles/><directors><director>http://dbpedia.org/resource/Raoul_Walsh</director></directors><writers><writer>http://dbpedia.org/resource/Raoul_Walsh</writer><writer>http://dbpedia.org/resource/Prosper_M%C3%A9rim%C3%A9e</writer></writers><actors><actor>http://dbpedia.org/resource/Theda_Bara</actor></actors></film><film><id>http://dbpedia.org/resource/Fireball_500</id><titles/><directors><director>http://dbpedia.org/resource/Leo_Townsend_%28director%29</director></directors><writers><writer>http://dbpedia.org/resource/William_Asher</writer></writers><actors><actor>http://dbpedia.org/resource/Fabian_%28entertainer%29</actor><actor>http://dbpedia.org/resource/Frankie_Avalon</actor><actor>http://dbpedia.org/resource/Chill_Wills</actor><actor>http://dbpedia.org/resource/Annette_Funicello</actor></actors></film><film><id>http://dbpedia.org/resource/The_Tiger_Woman_%281917_film%29</id><titles/><directors><director>http://dbpedia.org/resource/J._Gordon_Edwards</director><director>http://dbpedia.org/resource/George_Bellamy_%28actor%29</director></directors><writers/><actors><actor>http://dbpedia.org/resource/Edward_Roseman</actor><actor>http://dbpedia.org/resource/Theda_Bara</actor></actors></film><film><id>http://dbpedia.org/resource/Copperhead_%28film%29</id><titles/><directors/><writers/><actors><actor>http://dbpedia.org/resource/Brad_Johnson_%28actor%29</actor></actors></film><film><id>http://dbpedia.org/resource/Bustin%27_Down_The_Door</id><titles/><directors/><writers/><actors><actor>http://dbpedia.org/resource/Shaun_Tomson</actor><actor>http://dbpedia.org/resource/Ian_Cairns</actor><actor>http://dbpedia.org/resource/Mark_Richards</actor></actors></film><film><id>http://dbpedia.org/resource/Madame_Du_Barry_%281917_film%29</id><titles/><directors><director>http://dbpedia.org/resource/J._Gordon_Edwards</director></directors><writers><writer>http://dbpedia.org/resource/Alexandre_Dumas%2C_p%C3%A8re</writer></writers><actors><actor>http://dbpedia.org/resource/Charles_Clary</actor><actor>http://dbpedia.org/resource/Theda_Bara</actor></actors></film><film><id>http://dbpedia.org/resource/The_Forbidden_Path</id><titles/><directors><director>http://dbpedia.org/resource/J._Gordon_Edwards</director></directors><writers><writer>http://dbpedia.org/resource/E._Lloyd_Sheldon</writer></writers><actors><actor>http://dbpedia.org/resource/Theda_Bara</actor><actor>http://dbpedia.org/resource/Hugh_Thompson_%28actor%29</actor></actors></film><film><id>http://dbpedia.org/resource/Chat_Room_%28film%29</id><titles/><directors><director>http://dbpedia.org/resource/Barry_Bowles</director></directors><writers><writer>http://dbpedia.org/resource/Carl_Washington</writer></writers><actors><actor>http://dbpedia.org/resource/Brian_Hooks</actor><actor>http://dbpedia.org/resource/Christopher_Richards</actor><actor>http://dbpedia.org/resource/Troy_Winbush</actor><actor>http://dbpedia.org/resource/Deya_Simone</actor><actor>http://dbpedia.org/resource/Darryl_Brunson</actor></actors></film><film><id>http://dbpedia.org/resource/Dough_Boys_%28film%29</id><titles/><directors/><writers><writer>http://dbpedia.org/resource/Preston_A._Whitmore_II</writer></writers><actors><actor>http://dbpedia.org/resource/Wood_Harris</actor><actor>http://dbpedia.org/resource/Kirk_Jones</actor><actor>http://dbpedia.org/resource/Reagan_Gomez-Preston</actor></actors></film><film><id>http://dbpedia.org/resource/Ambassador_Bill</id><titles/><directors><director>http://dbpedia.org/resource/Sam_Taylor_%28director%29</director></directors><writers><writer>http://dbpedia.org/resource/Guy_Bolton</writer></writers><actors><actor>http://dbpedia.org/resource/Ray_Milland</actor><actor>http://dbpedia.org/resource/Greta_Nissen</actor><actor>http://dbpedia.org/resource/Marguerite_Churchill</actor><actor>http://dbpedia.org/resource/Tad_Alexander</actor></actors></film><film><id>http://dbpedia.org/resource/The_Kid_%281910_film%29</id><titles/><directors><director>http://dbpedia.org/resource/Frank_Powell</director></directors><writers/><actors><actor>http://dbpedia.org/resource/Henry_B._Walthall</actor></actors></film><film><id>http://dbpedia.org/resource/Heart_Beats_of_Long_Ago</id><titles/><directors><director>http://dbpedia.org/resource/D._W._Griffith</director></directors><writers/><actors><actor>http://dbpedia.org/resource/George_Nichols_%28actor%29</actor></actors></film><film><id>http://dbpedia.org/resource/The_Lily_of_the_Tenements</id><titles/><directors><director>http://dbpedia.org/resource/D._W._Griffith</director></directors><writers/><actors><actor>http://dbpedia.org/resource/Clara_T._Bracy</actor></actors></film><film><id>http://dbpedia.org/resource/The_Country_Lovers</id><titles/><directors><director>http://dbpedia.org/resource/Mack_Sennett</director></directors><writers><writer>http://dbpedia.org/resource/Frank_E._Woods</writer></writers><actors><actor>http://dbpedia.org/resource/Blanche_Sweet</actor></actors></film><film><id>http://dbpedia.org/resource/We_Can%27t_Go_Home_Again</id><titles/><directors><director>http://dbpedia.org/resource/Nicholas_Ray</director></directors><writers/><actors/></film><film><id>http://dbpedia.org/resource/The_Primal_Call</id><titles/><directors><director>http://dbpedia.org/resource/D._W._Griffith</director></directors><writers/><actors><actor>http://dbpedia.org/resource/Wilfred_Lucas</actor></actors></film><film><id>http://dbpedia.org/resource/How_to_Train_Your_Dragon_%28film%29</id><titles/><directors><director>http://dbpedia.org/resource/Dean_DeBlois</director><director>http://dbpedia.org/resource/Chris_Sanders_%28director%29</director></directors><writers><writer>http://dbpedia.org/resource/Peter_Tolan</writer><writer>http://dbpedia.org/resource/Dean_DeBlois</writer><writer>http://dbpedia.org/resource/Cressida_Cowell</writer></writers><actors><actor>http://dbpedia.org/resource/Gerard_Butler</actor><actor>http://dbpedia.org/resource/Jay_Baruchel</actor><actor>http://dbpedia.org/resource/Craig_Ferguson</actor><actor>http://dbpedia.org/resource/America_Ferrera</actor><actor>http://dbpedia.org/resource/Jonah_Hill</actor><actor>http://dbpedia.org/resource/Christopher_Mintz-Plasse</actor></actors></film><film><id>http://dbpedia.org/resource/The_Miser%27s_Heart</id><titles/><directors><director>http://dbpedia.org/resource/D._W._Griffith</director></directors><writers/><actors><actor>http://dbpedia.org/resource/Blanche_Sweet</actor></actors></film><film><id>http://dbpedia.org/resource/The_Punishment_%28film%29</id><titles/><directors><director>http://dbpedia.org/resource/D._W._Griffith</director></directors><writers/><actors><actor>http://dbpedia.org/resource/Blanche_Sweet</actor><actor>http://dbpedia.org/resource/J._Jiquel_Lanoe</actor></actors></film><film><id>http://dbpedia.org/resource/The_Lesser_Evil</id><titles/><directors><director>http://dbpedia.org/resource/D._W._Griffith</director></directors><writers/><actors><actor>http://dbpedia.org/resource/Edwin_August</actor><actor>http://dbpedia.org/resource/Blanche_Sweet</actor></actors></film><film><id>http://dbpedia.org/resource/The_Chief%27s_Blanket</id><titles/><directors><director>http://dbpedia.org/resource/D._W._Griffith</director></directors><writers><writer>http://dbpedia.org/resource/Wilfred_Lucas</writer></writers><actors><actor>http://dbpedia.org/resource/Lionel_Barrymore</actor><actor>http://dbpedia.org/resource/Blanche_Sweet</actor></actors></film><film><id>http://dbpedia.org/resource/We_Are_Not_Alone_%28film%29</id><titles/><directors><director>http://dbpedia.org/resource/Edmund_Goulding</director></directors><writers><writer>http://dbpedia.org/resource/James_Hilton</writer></writers><actors><actor>http://dbpedia.org/resource/Paul_Muni</actor><actor>http://dbpedia.org/resource/Flora_Robson</actor><actor>http://dbpedia.org/resource/Jane_Bryan</actor></actors></film><film><id>http://dbpedia.org/resource/Felon_%28film%29</id><titles/><directors><director>http://dbpedia.org/resource/Ric_Roman_Waugh</director></directors><writers><writer>http://dbpedia.org/resource/Ric_Roman_Waugh</writer></writers><actors><actor>http://dbpedia.org/resource/Marisol_Nichols</actor><actor>http://dbpedia.org/resource/Stephen_Dorff</actor><actor>http://dbpedia.org/resource/Val_Kilmer</actor><actor>http://dbpedia.org/resource/Sam_Shepard</actor><actor>http://dbpedia.org/resource/Harold_Perrineau</actor><actor>http://dbpedia.org/resource/Anne_Archer</actor></actors></film><film><id>http://dbpedia.org/resource/The_Last_Moment</id><titles/><directors/><writers/><actors/></film><film><id>http://dbpedia.org/resource/Edge_of_the_City</id><titles/><directors><director>http://dbpedia.org/resource/Martin_Ritt</director></directors><writers><writer>http://dbpedia.org/resource/Robert_Alan_Aurthur</writer></writers><actors><actor>http://dbpedia.org/resource/John_Cassavetes</actor><actor>http://dbpedia.org/resource/Jack_Warden</actor><actor>http://dbpedia.org/resource/Sidney_Poitier</actor></actors></film><film><id>http://dbpedia.org/resource/The_Call_of_the_Wild_%281935_film%29</id><titles/><directors><director>http://dbpedia.org/resource/William_A._Wellman</director></directors><writers><writer>http://dbpedia.org/resource/Jack_London</writer><writer>http://dbpedia.org/resource/Gene_Fowler</writer><writer>http://dbpedia.org/resource/Leonard_Praskins</writer></writers><actors><actor>http://dbpedia.org/resource/Clark_Gable</actor><actor>http://dbpedia.org/resource/Loretta_Young</actor><actor>http://dbpedia.org/resource/Jack_Oakie</actor></actors></film><film><id>http://dbpedia.org/resource/The_Battle_of_Gettysburg_%281955_film%29</id><titles/><directors><director>http://dbpedia.org/resource/Herman_Hoffman</director></directors><writers><writer>http://dbpedia.org/resource/Dore_Schary</writer></writers><actors/></film><film><id>http://dbpedia.org/resource/The_Fountain_of_Youth_%28film%29</id><titles/><directors><director>http://dbpedia.org/resource/Orson_Welles</director></directors><writers><writer>http://dbpedia.org/resource/John_Collier_%28writer%29</writer><writer>http://dbpedia.org/resource/Orson_Welles</writer></writers><actors><actor>http://dbpedia.org/resource/Joi_Lansing</actor><actor>http://dbpedia.org/resource/Rick_Jason</actor><actor>http://dbpedia.org/resource/Dan_Tobin</actor></actors></film><film><id>http://dbpedia.org/resource/The_Hungry_Bachelors_Club</id><titles/><directors/><writers/><actors><actor>http://dbpedia.org/resource/Jorja_Fox</actor><actor>http://dbpedia.org/resource/Bill_Nunn</actor></actors></film><film><id>http://dbpedia.org/resource/Apes_of_Wrath</id><titles/><directors/><writers/><actors/></film><film><id>http://dbpedia.org/resource/Night_Must_Fall_%281937_film%29</id><titles/><directors><director>http://dbpedia.org/resource/Richard_Thorpe</director></directors><writers><writer>http://dbpedia.org/resource/Emlyn_Williams</writer><writer>http://dbpedia.org/resource/John_Van_Druten</writer></writers><actors><actor>http://dbpedia.org/resource/Robert_Montgomery_%28actor%29</actor><actor>http://dbpedia.org/resource/Rosalind_Russell</actor><actor>http://dbpedia.org/resource/May_Whitty</actor></actors></film><film><id>http://dbpedia.org/resource/Blue_Hill_Avenue</id><titles/><directors/><writers/><actors><actor>http://dbpedia.org/resource/Clarence_Williams_III</actor><actor>http://dbpedia.org/resource/William_Forsythe_%28actor%29</actor><actor>http://dbpedia.org/resource/Andrew_Divoff</actor><actor>http://dbpedia.org/resource/Allen_Payne</actor><actor>http://dbpedia.org/resource/Michael_Taliferro</actor><actor>http://dbpedia.org/resource/William_L._Johnson</actor></actors></film><film><id>http://dbpedia.org/resource/Gentlemen_Are_Born</id><titles/><directors><director>http://dbpedia.org/resource/Alfred_E._Green</director></directors><writers><writer>http://dbpedia.org/resource/Edward_Chodorov</writer><writer>http://dbpedia.org/resource/Robert_Lee_Johnson_%28writer%29</writer><writer>http://dbpedia.org/resource/Eugene_Solow</writer></writers><actors><actor>http://dbpedia.org/resource/Franchot_Tone</actor></actors></film><film><id>http://dbpedia.org/resource/God%27s_Step_Children</id><titles/><directors><director>http://dbpedia.org/resource/Oscar_Micheaux</director></directors><writers/><actors><actor>http://dbpedia.org/resource/Alice_B._Russell</actor><actor>http://dbpedia.org/resource/Ethel_Moses</actor><actor>http://dbpedia.org/resource/Gloria_Press</actor><actor>http://dbpedia.org/resource/Jacqueline_Lewis</actor><actor>http://dbpedia.org/resource/Carmen_Newsome</actor></actors></film><film><id>http://dbpedia.org/resource/She_Knew_All_the_Answers</id><titles/><directors/><writers/><actors/></film><film><id>http://dbpedia.org/resource/The_Mississippi_Gambler</id><titles/><directors/><writers/><actors/></film><film><id>http://dbpedia.org/resource/Trade_Winds_%281938_film%29</id><titles/><directors><director>http://dbpedia.org/resource/Tay_Garnett</director></directors><writers/><actors/></film><film><id>http://dbpedia.org/resource/Vogues_of_1938</id><titles/><directors><director>http://dbpedia.org/resource/Irving_Cummings</director></directors><writers/><actors/></film><film><id>http://dbpedia.org/resource/The_Guy_Who_Came_Back</id><titles/><directors/><writers/><actors/></film><film><id>http://dbpedia.org/resource/In_Search_of_the_Castaways_%28film%29</id><titles/><directors><director>http://dbpedia.org/resource/Robert_Stevenson_%28director%29</director></directors><writers><writer>http://dbpedia.org/resource/Jules_Verne</writer></writers><actors><actor>http://dbpedia.org/resource/Maurice_Chevalier</actor><actor>http://dbpedia.org/resource/Jack_Gwillim</actor><actor>http://dbpedia.org/resource/Hayley_Mills</actor><actor>http://dbpedia.org/resource/George_Sanders_%28actor%29</actor><actor>http://dbpedia.org/resource/Wilfrid_Hyde-White</actor></actors></film><film><id>http://dbpedia.org/resource/The_Man_Who_Broke_the_Bank_at_Monte_Carlo</id><titles/><directors><director>http://dbpedia.org/resource/Stephen_Roberts_%28director%29</director></directors><writers><writer>http://dbpedia.org/resource/Howard_Smith</writer></writers><actors><actor>http://dbpedia.org/resource/Joan_Bennett</actor><actor>http://dbpedia.org/resource/Colin_Clive</actor><actor>http://dbpedia.org/resource/Ronald_Colman</actor></actors></film><film><id>http://dbpedia.org/resource/There%27s_Always_Tomorrow</id><titles/><directors><director>http://dbpedia.org/resource/Douglas_Sirk</director></directors><writers><writer>http://dbpedia.org/resource/Bernard_C._Schoenfeld</writer></writers><actors><actor>http://dbpedia.org/resource/Fred_MacMurray</actor><actor>http://dbpedia.org/resource/Joan_Bennett</actor><actor>http://dbpedia.org/resource/Barbara_Stanwyck</actor></actors></film><film><id>http://dbpedia.org/resource/Two_in_a_Crowd</id><titles/><directors><director>http://dbpedia.org/resource/Alfred_E._Green</director></directors><writers><writer>http://dbpedia.org/resource/Lewis_R._Foster</writer><writer>http://dbpedia.org/resource/Melville_Baker</writer><writer>http://dbpedia.org/resource/Samuel_Hoffenstein</writer><writer>http://dbpedia.org/resource/Edward_E._Paramore_Jr.</writer></writers><actors/></film><film><id>http://dbpedia.org/resource/Flying_High_%281931_film%29</id><titles/><directors/><writers/><actors/></film><film><id>http://dbpedia.org/resource/Lorna_Doone_%281922_film%29</id><titles/><directors><director>http://dbpedia.org/resource/Maurice_Tourneur</director></directors><writers><writer>http://dbpedia.org/resource/Maurice_Tourneur</writer><writer>http://dbpedia.org/resource/Wyndham_Gittens</writer><writer>http://dbpedia.org/resource/Richard_Doddridge_Blackmore</writer><writer>http://dbpedia.org/resource/Cecil_G._Mumford</writer><writer>http://dbpedia.org/resource/Katherine_S._Reed</writer></writers><actors><actor>http://dbpedia.org/resource/Madge_Bellamy</actor><actor>http://dbpedia.org/resource/Jack_McDonald_%28actor%29</actor><actor>http://dbpedia.org/resource/John_Bowers</actor><actor>http://dbpedia.org/resource/Frank_Keenan</actor></actors></film><film><id>http://dbpedia.org/resource/Pink_Plasma</id><titles/><directors/><writers/><actors/></film><film><id>http://dbpedia.org/resource/What%27s_Cookin%27%3F</id><titles/><directors><director>http://dbpedia.org/resource/Edward_F._Cline</director></directors><writers><writer>http://dbpedia.org/resource/Jerome_Cady</writer></writers><actors><actor>http://dbpedia.org/resource/The_Andrews_Sisters</actor><actor>http://dbpedia.org/resource/Robert_Paige</actor><actor>http://dbpedia.org/resource/Jane_Frazee</actor><actor>http://dbpedia.org/resource/Gloria_Jean</actor></actors></film><film><id>http://dbpedia.org/resource/Divine_Food</id><titles/><directors/><writers/><actors/></film><film><id>http://dbpedia.org/resource/The_House_Bunny</id><titles/><directors><director>http://dbpedia.org/resource/Fred_Wolf_%28writer%29</director></directors><writers/><actors><actor>http://dbpedia.org/resource/Hugh_Hefner</actor><actor>http://dbpedia.org/resource/Rumer_Willis</actor><actor>http://dbpedia.org/resource/Katharine_McPhee</actor><actor>http://dbpedia.org/resource/Tyson_Ritter</actor><actor>http://dbpedia.org/resource/Anna_Faris</actor><actor>http://dbpedia.org/resource/Beverly_D%27Angelo</actor><actor>http://dbpedia.org/resource/Colin_Hanks</actor><actor>http://dbpedia.org/resource/Emma_Stone</actor><actor>http://dbpedia.org/resource/Kat_Dennings</actor><actor>http://dbpedia.org/resource/Christopher_McDonald_%28actor%29</actor></actors></film><film><id>http://dbpedia.org/resource/Never_Back_Down</id><titles/><directors><director>http://dbpedia.org/resource/Jeff_Wadlow</director></directors><writers/><actors><actor>http://dbpedia.org/resource/Djimon_Hounsou</actor><actor>http://dbpedia.org/resource/Sean_Faris</actor><actor>http://dbpedia.org/resource/Amber_Heard</actor><actor>http://dbpedia.org/resource/Cam_Gigandet</actor><actor>http://dbpedia.org/resource/Evan_Peters</actor></actors></film><film><id>http://dbpedia.org/resource/Laid_to_Rest_%28film%29</id><titles/><directors><director>http://dbpedia.org/resource/Robert_Hall_%28makeup_artist%29</director></directors><writers><writer>http://dbpedia.org/resource/Robert_Hall_%28makeup_artist%29</writer></writers><actors><actor>http://dbpedia.org/resource/Lena_Headey</actor><actor>http://dbpedia.org/resource/Bobbi_Sue_Luther</actor><actor>http://dbpedia.org/resource/Kevin_Gage_%28actor%29</actor></actors></film><film><id>http://dbpedia.org/resource/Castle_on_the_Hudson</id><titles/><directors><director>http://dbpedia.org/resource/Anatole_Litvak</director></directors><writers><writer>http://dbpedia.org/resource/Seton_I._Miller</writer><writer>http://dbpedia.org/resource/Lewis_E._Lawes</writer><writer>http://dbpedia.org/resource/Brown_Holmes</writer><writer>http://dbpedia.org/resource/Courtney_Terrett</writer></writers><actors><actor>http://dbpedia.org/resource/Ann_Sheridan</actor><actor>http://dbpedia.org/resource/John_Garfield</actor><actor>http://dbpedia.org/resource/Pat_O%27Brien_%28actor%29</actor><actor>http://dbpedia.org/resource/Burgess_Meredith</actor></actors></film><film><id>http://dbpedia.org/resource/Late_Last_Night_%28film%29</id><titles/><directors><director>http://dbpedia.org/resource/Steven_Brill</director></directors><writers/><actors><actor>http://dbpedia.org/resource/Emilio_Estevez</actor><actor>http://dbpedia.org/resource/Steven_Weber_%28actor%29</actor></actors></film><film><id>http://dbpedia.org/resource/Culture_Clash_in_AmeriCCa</id><titles/><directors/><writers/><actors/></film><film><id>http://dbpedia.org/resource/The_Halliday_Brand</id><titles/><directors><director>http://dbpedia.org/resource/Joseph_H._Lewis</director></directors><writers><writer>http://dbpedia.org/resource/George_W._George</writer><writer>http://dbpedia.org/resource/George_F._Slavin</writer></writers><actors><actor>http://dbpedia.org/resource/Joseph_Cotten</actor></actors></film><film><id>http://dbpedia.org/resource/Her_Jungle_Love</id><titles/><directors><director>http://dbpedia.org/resource/George_Archainbaud</director></directors><writers><writer>http://dbpedia.org/resource/Curt_Siodmak</writer><writer>http://dbpedia.org/resource/Gerald_Geraghty</writer></writers><actors><actor>http://dbpedia.org/resource/Dorothy_Lamour</actor></actors></film><film><id>http://dbpedia.org/resource/The_McConnell_Story</id><titles/><directors/><writers/><actors/></film><film><id>http://dbpedia.org/resource/The_Reading_Room</id><titles/><directors/><writers/><actors/></film><film><id>http://dbpedia.org/resource/Morning_Light</id><titles/><directors><director>http://dbpedia.org/resource/Mark_Monroe</director></directors><writers/><actors/></film><film><id>http://dbpedia.org/resource/His_Lordship%27s_Dilemma</id><titles/><directors/><writers/><actors/></film><film><id>http://dbpedia.org/resource/The_Sex_and_Violence_Family_Hour</id><titles/><directors/><writers/><actors/></film><film><id>http://dbpedia.org/resource/The_Guilt_of_Janet_Ames</id><titles/><directors><director>http://dbpedia.org/resource/Henry_Levin</director></directors><writers><writer>http://dbpedia.org/resource/Lenore_J._Coffee</writer><writer>http://dbpedia.org/resource/Allen_Rivkin</writer><writer>http://dbpedia.org/resource/Devery_Freeman</writer></writers><actors><actor>http://dbpedia.org/resource/Melvyn_Douglas</actor><actor>http://dbpedia.org/resource/Rosalind_Russell</actor></actors></film><film><id>http://dbpedia.org/resource/Crisis_%281950_film%29</id><titles/><directors><director>http://dbpedia.org/resource/Richard_Brooks</director></directors><writers><writer>http://dbpedia.org/resource/George_Tabori</writer></writers><actors><actor>http://dbpedia.org/resource/Jos%C3%A9_Ferrer</actor><actor>http://dbpedia.org/resource/Paula_Raymond</actor><actor>http://dbpedia.org/resource/Cary_Grant</actor></actors></film><film><id>http://dbpedia.org/resource/Midnight_Man_%281995_film%29</id><titles/><directors/><writers/><actors><actor>http://dbpedia.org/resource/Lorenzo_Lamas</actor><actor>http://dbpedia.org/resource/James_Lew</actor><actor>http://dbpedia.org/resource/Mako_%28actor%29</actor></actors></film><film><id>http://dbpedia.org/resource/Into_the_Blue_2:_The_Reef</id><titles/><directors><director>http://dbpedia.org/resource/Stephen_Herek</director></directors><writers/><actors><actor>http://dbpedia.org/resource/Audrina_Patridge</actor><actor>http://dbpedia.org/resource/Laura_Vandervoort</actor><actor>http://dbpedia.org/resource/Chris_Carmack</actor></actors></film><film><id>http://dbpedia.org/resource/Honeymoon_for_Three</id><titles/><directors/><writers/><actors/></film><film><id>http://dbpedia.org/resource/Dragonworld</id><titles/><directors><director>http://dbpedia.org/resource/Ted_Nicolaou</director></directors><writers><writer>http://dbpedia.org/resource/Ted_Nicolaou</writer></writers><actors><actor>http://dbpedia.org/resource/Courtland_Mead</actor><actor>http://dbpedia.org/resource/Janet_Henfrey</actor><actor>http://dbpedia.org/resource/Stuart_Campbell</actor></actors></film><film><id>http://dbpedia.org/resource/Vitamin_Pink</id><titles/><directors/><writers/><actors/></film><film><id>http://dbpedia.org/resource/Prisoner_of_Zenda%2C_Inc.</id><titles/><directors/><writers/><actors/></film><film><id>http://dbpedia.org/resource/The_Midnight_Man_%281974_film%29</id><titles/><directors/><writers/><actors/></film><film><id>http://dbpedia.org/resource/Jewel_Robbery</id><titles/><directors><director>http://dbpedia.org/resource/William_Dieterle</director></directors><writers><writer>http://dbpedia.org/resource/Erwin_S._Gelsey</writer><writer>http://dbpedia.org/resource/Ladislas_Fodor</writer><writer>http://dbpedia.org/resource/Bertram_Bloch</writer></writers><actors><actor>http://dbpedia.org/resource/Kay_Francis</actor><actor>http://dbpedia.org/resource/William_Powell</actor></actors></film><film><id>http://dbpedia.org/resource/Skyscraper_Souls</id><titles/><directors><director>http://dbpedia.org/resource/Edgar_Selwyn</director></directors><writers><writer>http://dbpedia.org/resource/Faith_Baldwin</writer><writer>http://dbpedia.org/resource/Elmer_Blaney_Harris</writer><writer>http://dbpedia.org/resource/C._Gardner_Sullivan</writer></writers><actors><actor>http://dbpedia.org/resource/Gregory_Ratoff</actor><actor>http://dbpedia.org/resource/Anita_Page</actor><actor>http://dbpedia.org/resource/Warren_William</actor><actor>http://dbpedia.org/resource/Maureen_O%27Sullivan</actor></actors></film><film><id>http://dbpedia.org/resource/Relentless_%281989_film%29</id><titles/><directors><director>http://dbpedia.org/resource/William_Lustig</director></directors><writers><writer>http://dbpedia.org/resource/Phil_Alden_Robinson</writer></writers><actors><actor>http://dbpedia.org/resource/Judd_Nelson</actor><actor>http://dbpedia.org/resource/Meg_Foster</actor><actor>http://dbpedia.org/resource/Ken_Lerner</actor><actor>http://dbpedia.org/resource/Leo_Rossi</actor><actor>http://dbpedia.org/resource/Robert_Loggia</actor><actor>http://dbpedia.org/resource/Patrick_O%27Bryan</actor></actors></film><film><id>http://dbpedia.org/resource/The_Human_Comedy_%28film%29</id><titles/><directors><director>http://dbpedia.org/resource/Clarence_Brown</director></directors><writers><writer>http://dbpedia.org/resource/William_Saroyan</writer><writer>http://dbpedia.org/resource/Howard_Estabrook</writer></writers><actors><actor>http://dbpedia.org/resource/Mickey_Rooney</actor></actors></film><film><id>http://dbpedia.org/resource/Edge_of_Darkness_%282010_film%29</id><titles/><directors><director>http://dbpedia.org/resource/Martin_Campbell</director></directors><writers><writer>http://dbpedia.org/resource/Troy_Kennedy_Martin</writer><writer>http://dbpedia.org/resource/William_Monahan</writer><writer>http://dbpedia.org/resource/Andrew_Bovell</writer></writers><actors><actor>http://dbpedia.org/resource/Ray_Winstone</actor><actor>http://dbpedia.org/resource/Bojana_Novakovic</actor><actor>http://dbpedia.org/resource/Danny_Huston</actor><actor>http://dbpedia.org/resource/Jay_O._Sanders</actor><actor>http://dbpedia.org/resource/Mel_Gibson</actor></actors></film><film><id>http://dbpedia.org/resource/Between_Love_and_Hate_%281993_film%29</id><titles/><directors/><writers/><actors/></film><film><id>http://dbpedia.org/resource/Genie_with_the_Light_Pink_Fur</id><titles/><directors/><writers/><actors/></film><film><id>http://dbpedia.org/resource/Torrents_of_Spring_%28film%29</id><titles/><directors><director>http://dbpedia.org/resource/Jerzy_Skolimowski</director></directors><writers><writer>http://dbpedia.org/resource/Jerzy_Skolimowski</writer><writer>http://dbpedia.org/resource/Ivan_Turgenev</writer></writers><actors><actor>http://dbpedia.org/resource/Timothy_Hutton</actor><actor>http://dbpedia.org/resource/Nastassja_Kinski</actor></actors></film><film><id>http://dbpedia.org/resource/The_Angel_Levine</id><titles/><directors/><writers/><actors/></film><film><id>http://dbpedia.org/resource/The_Canary_Murder_Case_%28film%29</id><titles/><directors><director>http://dbpedia.org/resource/Malcolm_St._Clair_%28filmmaker%29</director><director>http://dbpedia.org/resource/Frank_Tuttle</director></directors><writers><writer>http://dbpedia.org/resource/Herman_J._Mankiewicz</writer><writer>http://dbpedia.org/resource/S.S._Van_Dine</writer></writers><actors><actor>http://dbpedia.org/resource/Jean_Arthur</actor><actor>http://dbpedia.org/resource/Louise_Brooks</actor><actor>http://dbpedia.org/resource/William_Powell</actor></actors></film><film><id>http://dbpedia.org/resource/The_Foundling_%281916_film%29</id><titles/><directors><director>http://dbpedia.org/resource/John_B._O%27Brien</director></directors><writers><writer>http://dbpedia.org/resource/Frances_Marion</writer></writers><actors><actor>http://dbpedia.org/resource/Mary_Pickford</actor></actors></film><film><id>http://dbpedia.org/resource/The_Foundling_%281915_film%29</id><titles/><directors><director>http://dbpedia.org/resource/John_B._O%27Brien</director></directors><writers><writer>http://dbpedia.org/resource/Frances_Marion</writer></writers><actors><actor>http://dbpedia.org/resource/Mary_Pickford</actor></actors></film><film><id>http://dbpedia.org/resource/Poor_Little_Peppina</id><titles/><directors><director>http://dbpedia.org/resource/Sidney_Olcott</director></directors><writers/><actors><actor>http://dbpedia.org/resource/Mary_Pickford</actor></actors></film><film><id>http://dbpedia.org/resource/The_Eternal_Grind</id><titles/><directors><director>http://dbpedia.org/resource/John_B._O%27Brien</director></directors><writers/><actors><actor>http://dbpedia.org/resource/Mary_Pickford</actor></actors></film><film><id>http://dbpedia.org/resource/Hearts_Adrift</id><titles/><directors><director>http://dbpedia.org/resource/Edwin_S._Porter</director></directors><writers><writer>http://dbpedia.org/resource/Mary_Pickford</writer><writer>http://dbpedia.org/resource/Cyrus_Townsend_Brady</writer></writers><actors><actor>http://dbpedia.org/resource/Mary_Pickford</actor></actors></film><film><id>http://dbpedia.org/resource/The_Little_Drummer_Girl_%28film%29</id><titles/><directors><director>http://dbpedia.org/resource/George_Roy_Hill</director></directors><writers><writer>http://dbpedia.org/resource/Loring_Mandel</writer><writer>http://dbpedia.org/resource/John_le_Carr%C3%A9</writer></writers><actors><actor>http://dbpedia.org/resource/Diane_Keaton</actor></actors></film><film><id>http://dbpedia.org/resource/Edith%27s_Shopping_Bag</id><titles/><directors><director>http://dbpedia.org/resource/Charlie_Ludlow</director><director>http://dbpedia.org/resource/Peter_Koper</director><director>http://dbpedia.org/resource/Laurel_Douglas</director></directors><writers/><actors><actor>http://dbpedia.org/resource/Edith_Massey</actor><actor>http://dbpedia.org/resource/Dreamlanders</actor><actor>http://dbpedia.org/resource/John_Waters_%28filmmaker%29</actor></actors></film><film><id>http://dbpedia.org/resource/First_to_Fight_%28film%29</id><titles/><directors/><writers/><actors/></film><film><id>http://dbpedia.org/resource/Oliver_Twist_%281933_film%29</id><titles/><directors><director>http://dbpedia.org/resource/William_J._Cowen</director></directors><writers><writer>http://dbpedia.org/resource/Charles_Dickens</writer><writer>http://dbpedia.org/resource/Elizabeth_Meehan</writer></writers><actors/></film><film><id>http://dbpedia.org/resource/If_You_Could_Only_Cook</id><titles/><directors><director>http://dbpedia.org/resource/William_A._Seiter</director></directors><writers><writer>http://dbpedia.org/resource/Gertrude_Purcell</writer><writer>http://dbpedia.org/resource/F._Hugh_Herbert</writer><writer>http://dbpedia.org/resource/Howard_J._Green</writer></writers><actors><actor>http://dbpedia.org/resource/Jean_Arthur</actor><actor>http://dbpedia.org/resource/Herbert_Marshall</actor></actors></film><film><id>http://dbpedia.org/resource/Hobbs_End_%28film%29</id><titles/><directors/><writers/><actors/></film><film><id>http://dbpedia.org/resource/Nasty_Boys_%28film%29</id><titles/><directors/><writers/><actors/></film><film><id>http://dbpedia.org/resource/Dead_Man%27s_Folly_%28film%29</id><titles/><directors/><writers/><actors/></film><film><id>http://dbpedia.org/resource/The_Eternal_City_%281915_film%29</id><titles/><directors/><writers/><actors/></film><film><id>http://dbpedia.org/resource/The_Fairy_and_the_Waif</id><titles/><directors><director>http://dbpedia.org/resource/George_Irving_%28American_actor%29</director><director>http://dbpedia.org/resource/Marie_Hubert_Frohman</director></directors><writers/><actors><actor>http://dbpedia.org/resource/Mary_Miles_Minter</actor></actors></film><film><id>http://dbpedia.org/resource/Let%27s_Make_Music</id><titles/><directors><director>http://dbpedia.org/resource/Leslie_Goodwins</director></directors><writers><writer>http://dbpedia.org/resource/Nathanael_West</writer></writers><actors><actor>http://dbpedia.org/resource/Bob_Crosby</actor><actor>http://dbpedia.org/resource/Elisabeth_Risdon</actor></actors></film><film><id>http://dbpedia.org/resource/Lovely_Mary</id><titles/><directors/><writers/><actors><actor>http://dbpedia.org/resource/Mary_Miles_Minter</actor></actors></film><film><id>http://dbpedia.org/resource/Faith_%28film%29</id><titles/><directors><director>http://dbpedia.org/resource/James_Kirkwood%2C_Sr.</director></directors><writers/><actors><actor>http://dbpedia.org/resource/Mary_Miles_Minter</actor></actors></film><film><id>http://dbpedia.org/resource/The_Ballad_of_Josie</id><titles/><directors><director>http://dbpedia.org/resource/Andrew_V._McLaglen</director></directors><writers><writer>http://dbpedia.org/resource/Harold_Swanton</writer></writers><actors><actor>http://dbpedia.org/resource/Peter_Graves_%28actor%29</actor><actor>http://dbpedia.org/resource/George_Kennedy</actor><actor>http://dbpedia.org/resource/David_Hartman_%28TV_personality%29</actor><actor>http://dbpedia.org/resource/William_Talman_%28actor%29</actor><actor>http://dbpedia.org/resource/Doris_Day</actor><actor>http://dbpedia.org/resource/Andy_Devine</actor></actors></film><film><id>http://dbpedia.org/resource/Save_Me_%282007_film%29</id><titles/><directors><director>http://dbpedia.org/resource/Robert_Cary</director></directors><writers><writer>http://dbpedia.org/resource/Craig_Chester</writer><writer>http://dbpedia.org/resource/Robert_Desiderio</writer><writer>http://dbpedia.org/resource/Alan_Hines</writer></writers><actors><actor>http://dbpedia.org/resource/Stephen_Lang_%28actor%29</actor></actors></film><film><id>http://dbpedia.org/resource/Hornets%27_Nest</id><titles/><directors><director>http://dbpedia.org/resource/Phil_Karlson</director><director>http://dbpedia.org/resource/Franco_Cirino</director></directors><writers><writer>http://dbpedia.org/resource/S.S._Schweitzer</writer><writer>http://dbpedia.org/resource/Stanley_Colbert</writer></writers><actors><actor>http://dbpedia.org/resource/Sergio_Fantoni</actor><actor>http://dbpedia.org/resource/Giacomo_Rossi-Stuart</actor><actor>http://dbpedia.org/resource/Rock_Hudson</actor><actor>http://dbpedia.org/resource/Sylva_Koscina</actor><actor>http://dbpedia.org/resource/Jacques_Sernas</actor><actor>http://dbpedia.org/resource/Mark_Colleano</actor></actors></film><film><id>http://dbpedia.org/resource/Bachelor_Flat</id><titles/><directors><director>http://dbpedia.org/resource/Frank_Tashlin</director></directors><writers><writer>http://dbpedia.org/resource/Frank_Tashlin</writer></writers><actors><actor>http://dbpedia.org/resource/Terry-Thomas</actor><actor>http://dbpedia.org/resource/Tuesday_Weld</actor><actor>http://dbpedia.org/resource/Celeste_Holm</actor><actor>http://dbpedia.org/resource/Richard_Beymer</actor></actors></film><film><id>http://dbpedia.org/resource/The_Way_We_Live_Now_%28film%29</id><titles/><directors/><writers/><actors/></film><film><id>http://dbpedia.org/resource/The_Call_of_the_Wild_%281908_film%29</id><titles/><directors/><writers/><actors/></film><film><id>http://dbpedia.org/resource/Made_in_Paris</id><titles/><directors><director>http://dbpedia.org/resource/Boris_Sagal</director></directors><writers/><actors><actor>http://dbpedia.org/resource/Louis_Jourdan</actor><actor>http://dbpedia.org/resource/Richard_Crenna</actor><actor>http://dbpedia.org/resource/Ann-Margaret</actor></actors></film><film><id>http://dbpedia.org/resource/Berlin:_Live_at_St._Ann%27s_Warehouse</id><titles/><directors><director>http://dbpedia.org/resource/Julian_Schnabel</director></directors><writers/><actors><actor>http://dbpedia.org/resource/Emmanuelle_Seigner</actor><actor>http://dbpedia.org/resource/Lou_Reed</actor></actors></film><film><id>http://dbpedia.org/resource/Journey_into_Fear_%281943_film%29</id><titles/><directors><director>http://dbpedia.org/resource/Norman_Foster_%28director%29</director></directors><writers><writer>http://dbpedia.org/resource/Orson_Welles</writer><writer>http://dbpedia.org/resource/Ben_Hecht</writer><writer>http://dbpedia.org/resource/Eric_Ambler</writer></writers><actors><actor>http://dbpedia.org/resource/Ruth_Warrick</actor><actor>http://dbpedia.org/resource/Joseph_Cotten</actor><actor>http://dbpedia.org/resource/Orson_Welles</actor><actor>http://dbpedia.org/resource/Dolores_del_R%C3%ADo</actor></actors></film><film><id>http://dbpedia.org/resource/Seein%27_Things</id><titles/><directors><director>http://dbpedia.org/resource/Robert_F._McGowan</director></directors><writers><writer>http://dbpedia.org/resource/Hal_Roach</writer><writer>http://dbpedia.org/resource/H._M._Walker</writer></writers><actors/></film><film><id>http://dbpedia.org/resource/Commencement_Day</id><titles/><directors><director>http://dbpedia.org/resource/Robert_F._McGowan</director><director>http://dbpedia.org/resource/Mark_Goldaine</director></directors><writers><writer>http://dbpedia.org/resource/H._M._Walker</writer></writers><actors/></film><film><id>http://dbpedia.org/resource/It%27s_a_Bear</id><titles/><directors><director>http://dbpedia.org/resource/Robert_F._McGowan</director></directors><writers><writer>http://dbpedia.org/resource/Hal_Roach</writer><writer>http://dbpedia.org/resource/H._M._Walker</writer></writers><actors/></film><film><id>http://dbpedia.org/resource/High_Society_%281924_film%29</id><titles/><directors><director>http://dbpedia.org/resource/Robert_F._McGowan</director></directors><writers><writer>http://dbpedia.org/resource/Frank_Capra</writer><writer>http://dbpedia.org/resource/Hal_Roach</writer><writer>http://dbpedia.org/resource/H._M._Walker</writer></writers><actors/></film><film><id>http://dbpedia.org/resource/The_Love_Bug_%281925_film%29</id><titles/><directors><director>http://dbpedia.org/resource/Robert_F._McGowan</director></directors><writers><writer>http://dbpedia.org/resource/Hal_Roach</writer><writer>http://dbpedia.org/resource/H._M._Walker</writer></writers><actors/></film><film><id>http://dbpedia.org/resource/One_Wild_Ride</id><titles/><directors><director>http://dbpedia.org/resource/Robert_F._McGowan</director></directors><writers><writer>http://dbpedia.org/resource/Hal_Roach</writer><writer>http://dbpedia.org/resource/H._M._Walker</writer></writers><actors/></film><film><id>http://dbpedia.org/resource/Love_My_Dog</id><titles/><directors><director>http://dbpedia.org/resource/Robert_F._McGowan</director></directors><writers><writer>http://dbpedia.org/resource/Hal_Roach</writer><writer>http://dbpedia.org/resource/H._M._Walker</writer></writers><actors/></film><film><id>http://dbpedia.org/resource/Chicken_Feed</id><titles/><directors><director>http://dbpedia.org/resource/Robert_A._McGowan</director><director>http://dbpedia.org/resource/Charles_Oelze</director></directors><writers><writer>http://dbpedia.org/resource/Hal_Roach</writer><writer>http://dbpedia.org/resource/H._M._Walker</writer></writers><actors/></film><film><id>http://dbpedia.org/resource/Spook_Spoofing</id><titles/><directors><director>http://dbpedia.org/resource/Robert_F._McGowan</director></directors><writers><writer>http://dbpedia.org/resource/Robert_A._McGowan</writer><writer>http://dbpedia.org/resource/Reed_Heustis</writer></writers><actors/></film><film><id>http://dbpedia.org/resource/Rainy_Days_%28film%29</id><titles/><directors><director>http://dbpedia.org/resource/Robert_A._McGowan</director></directors><writers><writer>http://dbpedia.org/resource/Robert_A._McGowan</writer><writer>http://dbpedia.org/resource/Reed_Heustis</writer></writers><actors/></film><film><id>http://dbpedia.org/resource/Crazy_House_%281928_film%29</id><titles/><directors><director>http://dbpedia.org/resource/Robert_F._McGowan</director></directors><writers><writer>http://dbpedia.org/resource/H._M._Walker</writer></writers><actors/></film><film><id>http://dbpedia.org/resource/School_Begins</id><titles/><directors><director>http://dbpedia.org/resource/Robert_A._McGowan</director></directors><writers><writer>http://dbpedia.org/resource/H._M._Walker</writer><writer>http://dbpedia.org/resource/Robert_A._McGowan</writer></writers><actors/></film><film><id>http://dbpedia.org/resource/The_Spanking_Age</id><titles/><directors><director>http://dbpedia.org/resource/Robert_F._McGowan</director></directors><writers><writer>http://dbpedia.org/resource/H._M._Walker</writer><writer>http://dbpedia.org/resource/Robert_A._McGowan</writer></writers><actors/></film><film><id>http://dbpedia.org/resource/Cat%2C_Dog_%26_Co.</id><titles/><directors><director>http://dbpedia.org/resource/Robert_A._McGowan</director></directors><writers><writer>http://dbpedia.org/resource/H._M._Walker</writer><writer>http://dbpedia.org/resource/Robert_A._McGowan</writer></writers><actors/></film><film><id>http://dbpedia.org/resource/Lazy_Days_%28film%29</id><titles/><directors><director>http://dbpedia.org/resource/Robert_F._McGowan</director></directors><writers/><actors><actor>http://dbpedia.org/resource/Jean_Darling</actor><actor>http://dbpedia.org/resource/Harry_Spear</actor><actor>http://dbpedia.org/resource/Mary_Ann_Jackson</actor><actor>http://dbpedia.org/resource/Allen_Hoskins</actor><actor>http://dbpedia.org/resource/Norman_Chaney</actor><actor>http://dbpedia.org/resource/Joe_Cobb</actor><actor>http://dbpedia.org/resource/Junior_Allen</actor><actor>http://dbpedia.org/resource/Jannie_Hoskins</actor></actors></film><film><id>http://dbpedia.org/resource/Alibi_Bye_Bye</id><titles/><directors/><writers><writer>http://dbpedia.org/resource/Bobby_Clark_%28comedian%29</writer></writers><actors><actor>http://dbpedia.org/resource/Dorothy_Granger</actor><actor>http://dbpedia.org/resource/Bobby_Clark_%28comedian%29</actor><actor>http://dbpedia.org/resource/Bud_Jamison</actor><actor>http://dbpedia.org/resource/Tom_Kennedy_%28American_actor%29</actor><actor>http://dbpedia.org/resource/Paul_McCullough</actor></actors></film><film><id>http://dbpedia.org/resource/The_First_Seven_Years</id><titles/><directors><director>http://dbpedia.org/resource/Robert_F._McGowan</director></directors><writers><writer>http://dbpedia.org/resource/Robert_A._McGowan</writer></writers><actors/></film><film><id>http://dbpedia.org/resource/Dogs_is_Dogs</id><titles/><directors><director>http://dbpedia.org/resource/Robert_F._McGowan</director></directors><writers><writer>http://dbpedia.org/resource/H._M._Walker</writer></writers><actors/></film><film><id>http://dbpedia.org/resource/Choo-Choo%21</id><titles/><directors><director>http://dbpedia.org/resource/Robert_F._McGowan</director></directors><writers><writer>http://dbpedia.org/resource/Hal_Roach</writer><writer>http://dbpedia.org/resource/H._M._Walker</writer></writers><actors/></film><film><id>http://dbpedia.org/resource/Birthday_Blues</id><titles/><directors><director>http://dbpedia.org/resource/Robert_F._McGowan</director></directors><writers/><actors/></film><film><id>http://dbpedia.org/resource/Bedtime_Worries</id><titles/><directors><director>http://dbpedia.org/resource/Robert_F._McGowan</director></directors><writers/><actors/></film><film><id>http://dbpedia.org/resource/Hi%27-Neighbor%21</id><titles/><directors><director>http://dbpedia.org/resource/Gus_Meins</director></directors><writers/><actors><actor>http://dbpedia.org/resource/Scotty_Beckett</actor><actor>http://dbpedia.org/resource/Jerry_Tucker</actor><actor>http://dbpedia.org/resource/George_McFarland</actor><actor>http://dbpedia.org/resource/Matthew_Beard_%28American_actor%29</actor><actor>http://dbpedia.org/resource/Tommy_Bond</actor><actor>http://dbpedia.org/resource/Wally_Albright</actor><actor>http://dbpedia.org/resource/Jackie_Lynn_Taylor</actor></actors></film><film><id>http://dbpedia.org/resource/For_Pete%27s_Sake%21</id><titles/><directors><director>http://dbpedia.org/resource/Gus_Meins</director></directors><writers/><actors/></film><film><id>http://dbpedia.org/resource/Honky_Donkey</id><titles/><directors><director>http://dbpedia.org/resource/Gus_Meins</director></directors><writers/><actors/></film><film><id>http://dbpedia.org/resource/Mama%27s_Little_Pirate</id><titles/><directors><director>http://dbpedia.org/resource/Gus_Meins</director></directors><writers/><actors/></film><film><id>http://dbpedia.org/resource/Shrimps_for_a_Day</id><titles/><directors><director>http://dbpedia.org/resource/Gus_Meins</director></directors><writers/><actors/></film><film><id>http://dbpedia.org/resource/Little_Papa</id><titles/><directors><director>http://dbpedia.org/resource/Gus_Meins</director></directors><writers/><actors/></film><film><id>http://dbpedia.org/resource/Too_Soon_to_Love</id><titles/><directors/><writers/><actors/></film><film><id>http://dbpedia.org/resource/Our_Gang_Follies_of_1936</id><titles/><directors><director>http://dbpedia.org/resource/Gus_Meins</director></directors><writers/><actors><actor>http://dbpedia.org/resource/Scotty_Beckett</actor><actor>http://dbpedia.org/resource/George_McFarland</actor><actor>http://dbpedia.org/resource/Eugene_Gordon_Lee</actor><actor>http://dbpedia.org/resource/Darla_Hood</actor><actor>http://dbpedia.org/resource/Carl_Switzer</actor><actor>http://dbpedia.org/resource/Billie_Thomas</actor></actors></film><film><id>http://dbpedia.org/resource/Second_Childhood_%28film%29</id><titles/><directors><director>http://dbpedia.org/resource/Gus_Meins</director></directors><writers/><actors><actor>http://dbpedia.org/resource/George_McFarland</actor><actor>http://dbpedia.org/resource/Eugene_Gordon_Lee</actor><actor>http://dbpedia.org/resource/Sidney_Bracey</actor><actor>http://dbpedia.org/resource/Zeffie_Tilbury</actor><actor>http://dbpedia.org/resource/Darla_Hood</actor><actor>http://dbpedia.org/resource/Carl_Switzer</actor><actor>http://dbpedia.org/resource/Billie_Thomas</actor><actor>http://dbpedia.org/resource/Dickie_De_Nuet</actor><actor>http://dbpedia.org/resource/Gretta_Gould</actor></actors></film><film><id>http://dbpedia.org/resource/Two_Too_Young</id><titles/><directors><director>http://dbpedia.org/resource/Gordon_Douglas_%28director%29</director></directors><writers><writer>http://dbpedia.org/resource/Louis_McManus</writer><writer>http://dbpedia.org/resource/Hal_Law</writer></writers><actors><actor>http://dbpedia.org/resource/George_McFarland</actor><actor>http://dbpedia.org/resource/Eugene_Gordon_Lee</actor><actor>http://dbpedia.org/resource/Rosina_Lawrence</actor><actor>http://dbpedia.org/resource/Carl_Switzer</actor><actor>http://dbpedia.org/resource/Billie_Thomas</actor></actors></film><film><id>http://dbpedia.org/resource/Spooky_Hooky</id><titles/><directors><director>http://dbpedia.org/resource/Gordon_Douglas_%28director%29</director></directors><writers><writer>http://dbpedia.org/resource/Hal_Roach</writer></writers><actors/></film><film><id>http://dbpedia.org/resource/Hearts_Are_Thumps</id><titles/><directors><director>http://dbpedia.org/resource/Gordon_Douglas_%28director%29</director></directors><writers/><actors/></film><film><id>http://dbpedia.org/resource/Three_Smart_Boys</id><titles/><directors><director>http://dbpedia.org/resource/Gordon_Douglas_%28director%29</director></directors><writers/><actors/></film><film><id>http://dbpedia.org/resource/Three_Men_in_a_Tub</id><titles/><directors><director>http://dbpedia.org/resource/Nate_Watt</director></directors><writers/><actors/></film><film><id>http://dbpedia.org/resource/The_Shooter_%281995_film%29</id><titles/><directors><director>http://dbpedia.org/resource/Ted_Kotcheff</director></directors><writers><writer>http://dbpedia.org/resource/Yves_Andr%C3%A9_Martin</writer></writers><actors><actor>http://dbpedia.org/resource/Dolph_Lundgren</actor></actors></film><film><id>http://dbpedia.org/resource/Nicky%27s_Game</id><titles/><directors/><writers/><actors><actor>http://dbpedia.org/resource/Burt_Young</actor><actor>http://dbpedia.org/resource/Alexie_Gilmore</actor><actor>http://dbpedia.org/resource/John_Ventimiglia</actor><actor>http://dbpedia.org/resource/Lev_Gorn</actor></actors></film><film><id>http://dbpedia.org/resource/The_Peacekeeper</id><titles/><directors><director>http://dbpedia.org/resource/Fr%C3%A9d%C3%A9ric_Forestier</director></directors><writers><writer>http://dbpedia.org/resource/Robert_Geoffrion</writer></writers><actors><actor>http://dbpedia.org/resource/Dolph_Lundgren</actor></actors></film><film><id>http://dbpedia.org/resource/Young_at_Heart_%281995_film%29</id><titles/><directors><director>http://dbpedia.org/resource/Allan_Arkush</director></directors><writers><writer>http://dbpedia.org/resource/Judith_Paige_Mitchell</writer></writers><actors/></film><film><id>http://dbpedia.org/resource/My_Lover_My_Son</id><titles/><directors><director>http://dbpedia.org/resource/John_Newland</director></directors><writers/><actors><actor>http://dbpedia.org/resource/Romy_Schneider</actor><actor>http://dbpedia.org/resource/Dennis_Waterman</actor></actors></film><film><id>http://dbpedia.org/resource/National_Treasure_%28franchise%29</id><titles/><directors/><writers/><actors/></film><film><id>http://dbpedia.org/resource/The_Spirit_of_Culver</id><titles/><directors><director>http://dbpedia.org/resource/Joseph_Santley</director></directors><writers><writer>http://dbpedia.org/resource/Tom_Buckingham</writer><writer>http://dbpedia.org/resource/Whitney_Bolton</writer></writers><actors><actor>http://dbpedia.org/resource/Jackie_Cooper</actor><actor>http://dbpedia.org/resource/Freddie_Bartholomew</actor></actors></film><film><id>http://dbpedia.org/resource/Party_Fever</id><titles/><directors><director>http://dbpedia.org/resource/George_Sidney</director></directors><writers><writer>http://dbpedia.org/resource/Robert_A._McGowan</writer><writer>http://dbpedia.org/resource/Hal_Law</writer></writers><actors/></film><film><id>http://dbpedia.org/resource/Aladdin%27s_Lantern</id><titles/><directors><director>http://dbpedia.org/resource/George_Sidney</director></directors><writers><writer>http://dbpedia.org/resource/Robert_A._McGowan</writer><writer>http://dbpedia.org/resource/Hal_Law</writer></writers><actors/></film><film><id>http://dbpedia.org/resource/Practical_Jokers</id><titles/><directors><director>http://dbpedia.org/resource/George_Sidney</director></directors><writers><writer>http://dbpedia.org/resource/Robert_A._McGowan</writer><writer>http://dbpedia.org/resource/Hal_Law</writer></writers><actors/></film><film><id>http://dbpedia.org/resource/Clown_Princes</id><titles/><directors><director>http://dbpedia.org/resource/George_Sidney</director></directors><writers><writer>http://dbpedia.org/resource/Robert_A._McGowan</writer><writer>http://dbpedia.org/resource/Hal_Law</writer></writers><actors><actor>http://dbpedia.org/resource/George_McFarland</actor><actor>http://dbpedia.org/resource/Eugene_Gordon_Lee</actor><actor>http://dbpedia.org/resource/Leonard_Landy</actor><actor>http://dbpedia.org/resource/Darla_Hood</actor><actor>http://dbpedia.org/resource/Carl_Switzer</actor><actor>http://dbpedia.org/resource/Billie_Thomas</actor><actor>http://dbpedia.org/resource/Clarence_Wilson</actor><actor>http://dbpedia.org/resource/Shirley_Coates</actor></actors></film><film><id>http://dbpedia.org/resource/Moll_Flanders_%281996_film%29</id><titles/><directors><director>http://dbpedia.org/resource/Pen_Densham</director></directors><writers/><actors><actor>http://dbpedia.org/resource/Morgan_Freeman</actor><actor>http://dbpedia.org/resource/Jeremy_Brett</actor><actor>http://dbpedia.org/resource/Robin_Wright_Penn</actor><actor>http://dbpedia.org/resource/John_Lynch</actor><actor>http://dbpedia.org/resource/Stockard_Channing</actor></actors></film><film><id>http://dbpedia.org/resource/Habit_%28film%29</id><titles/><directors/><writers/><actors/></film><film><id>http://dbpedia.org/resource/Oblivion_2:_Backlash</id><titles/><directors/><writers/><actors/></film><film><id>http://dbpedia.org/resource/A_Bunny%27s_Tale</id><titles/><directors/><writers/><actors/></film><film><id>http://dbpedia.org/resource/Time_Out_for_Lessons</id><titles/><directors><director>http://dbpedia.org/resource/Edward_Cahn_%28director%29</director><director>http://dbpedia.org/resource/Bud_Murray</director></directors><writers><writer>http://dbpedia.org/resource/Robert_A._McGowan</writer><writer>http://dbpedia.org/resource/Hal_Law</writer></writers><actors/></film><film><id>http://dbpedia.org/resource/Woman%27s_World_%28film%29</id><titles/><directors><director>http://dbpedia.org/resource/Jean_Negulesco</director></directors><writers><writer>http://dbpedia.org/resource/Russel_Crouse</writer><writer>http://dbpedia.org/resource/Howard_Lindsay</writer><writer>http://dbpedia.org/resource/Claude_Binyon</writer><writer>http://dbpedia.org/resource/Mary_Loos</writer><writer>http://dbpedia.org/resource/Richard_Sale_%28director%29</writer></writers><actors><actor>http://dbpedia.org/resource/Fred_MacMurray</actor><actor>http://dbpedia.org/resource/Clifton_Webb</actor><actor>http://dbpedia.org/resource/June_Allyson</actor><actor>http://dbpedia.org/resource/Lauren_Bacall</actor><actor>http://dbpedia.org/resource/Cornel_Wilde</actor><actor>http://dbpedia.org/resource/Van_Heflin</actor><actor>http://dbpedia.org/resource/Arlene_Dahl</actor></actors></film><film><id>http://dbpedia.org/resource/Bubbling_Troubles</id><titles/><directors><director>http://dbpedia.org/resource/Edward_Cahn_%28director%29</director></directors><writers><writer>http://dbpedia.org/resource/Robert_A._McGowan</writer><writer>http://dbpedia.org/resource/Hal_Law</writer></writers><actors/></film><film><id>http://dbpedia.org/resource/The_Big_Premiere</id><titles/><directors><director>http://dbpedia.org/resource/Edward_Cahn_%28director%29</director></directors><writers><writer>http://dbpedia.org/resource/Robert_A._McGowan</writer><writer>http://dbpedia.org/resource/Hal_Law</writer></writers><actors/></film><film><id>http://dbpedia.org/resource/Satan%27s_Triangle</id><titles/><directors/><writers/><actors/></film><film><id>http://dbpedia.org/resource/Waldo%27s_Last_Stand</id><titles/><directors><director>http://dbpedia.org/resource/Edward_Cahn_%28director%29</director><director>http://dbpedia.org/resource/Steven_Granger</director></directors><writers><writer>http://dbpedia.org/resource/Robert_A._McGowan</writer><writer>http://dbpedia.org/resource/Hal_Law</writer></writers><actors/></film><film><id>http://dbpedia.org/resource/Fightin%27_Fools</id><titles/><directors><director>http://dbpedia.org/resource/Edward_Cahn_%28director%29</director></directors><writers><writer>http://dbpedia.org/resource/Robert_A._McGowan</writer><writer>http://dbpedia.org/resource/Hal_Law</writer></writers><actors/></film><film><id>http://dbpedia.org/resource/Electrical_Skeletal</id><titles/><directors/><writers/><actors/></film><film><id>http://dbpedia.org/resource/The_Pied_Piper_of_Hamelin_%281957_film%29</id><titles/><directors><director>http://dbpedia.org/resource/Bretaigne_Windust</director></directors><writers><writer>http://dbpedia.org/resource/Robert_Browning</writer><writer>http://dbpedia.org/resource/Irving_Taylor</writer><writer>http://dbpedia.org/resource/Hal_Stanley</writer></writers><actors/></film><film><id>http://dbpedia.org/resource/Going_to_Press</id><titles/><directors><director>http://dbpedia.org/resource/Edward_Cahn_%28director%29</director></directors><writers><writer>http://dbpedia.org/resource/Robert_A._McGowan</writer><writer>http://dbpedia.org/resource/Hal_Law</writer></writers><actors/></film><film><id>http://dbpedia.org/resource/Election_Daze</id><titles/><directors><director>http://dbpedia.org/resource/Herbert_Glazer</director></directors><writers><writer>http://dbpedia.org/resource/Robert_A._McGowan</writer><writer>http://dbpedia.org/resource/Hal_Law</writer></writers><actors/></film><film><id>http://dbpedia.org/resource/Calling_All_Kids</id><titles/><directors><director>http://dbpedia.org/resource/Sam_Baerwitz</director></directors><writers><writer>http://dbpedia.org/resource/Robert_A._McGowan</writer><writer>http://dbpedia.org/resource/Hal_Law</writer></writers><actors/></film>
<films>